scription/CHANGES
scription/LICENSE
scription/__init__.py
scription/test.py
scription-0.86.27.dist-info/METADATA
scription-0.86.27.dist-info/WHEEL
scription-0.86.27.dist-info/top_level.txt
scription-0.86.27.dist-info/RECORD
